ou_xml_validator/__init__.py
ou_xml_validator/cli.py
ou_xml_validator/md_tools.py
ou_xml_validator/obt.py
ou_xml_validator/ouxml2md.py
ou_xml_validator/ouxml2mm.py
ou_xml_validator/ouxml2tw.py
ou_xml_validator/utils.py
ou_xml_validator/xml_validator.py
ou_xml_validator/xml_xslt.py
ou_xml_validator/mermaid-cli/package-lock.json
ou_xml_validator/mermaid-cli/package.json
ou_xml_validator/schemas/OUIntermediateSchema.xsd
ou_xml_validator/schemas/mathml3/xsd/mathml3-common.xsd
ou_xml_validator/schemas/mathml3/xsd/mathml3-content.xsd
ou_xml_validator/schemas/mathml3/xsd/mathml3-presentation.xsd
ou_xml_validator/schemas/mathml3/xsd/mathml3-strict-content.xsd
ou_xml_validator/schemas/mathml3/xsd/mathml3.xsd
ou_xml_validator/templates/ouxml_template.xml
ou_xml_validator/xslt/ouxml2jbindex.xslt
ou_xml_validator/xslt/ouxml2jbtoc.xslt
ou_xml_validator/xslt/ouxml2myst.xslt
ou_xml_validator/xslt/ouxml2tw.xslt
ou_xml_validator/xslt/sphinxXml2ouxml.xslt
ou_xml_validator-0.0.3.dist-info/LICENSE
ou_xml_validator-0.0.3.dist-info/METADATA
ou_xml_validator-0.0.3.dist-info/WHEEL
ou_xml_validator-0.0.3.dist-info/entry_points.txt
ou_xml_validator-0.0.3.dist-info/top_level.txt
ou_xml_validator-0.0.3.dist-info/RECORD
